{
  "Core": {
    "animation": {
      "duration": {
        "xs2": {
          "value": "0ms",
          "type": "other"
        },
        "xs": {
          "value": "50ms",
          "type": "other"
        },
        "sm": {
          "value": "100ms",
          "type": "other"
        },
        "md": {
          "value": "150ms",
          "type": "other"
        },
        "lg": {
          "value": "200ms",
          "type": "other"
        },
        "xl": {
          "value": "300ms",
          "type": "other"
        },
        "xl2": {
          "value": "400ms",
          "type": "other"
        },
        "xl3": {
          "value": "500ms",
          "type": "other"
        },
        "g": {
          "value": "5000ms",
          "type": "other"
        }
      },
      "delay": {
        "xs2": {
          "value": "0ms",
          "type": "other"
        },
        "xs": {
          "value": "50ms",
          "type": "other"
        },
        "sm": {
          "value": "100ms",
          "type": "other"
        },
        "md": {
          "value": "150ms",
          "type": "other"
        },
        "lg": {
          "value": "200ms",
          "type": "other"
        },
        "xl": {
          "value": "300ms",
          "type": "other"
        },
        "xl2": {
          "value": "400ms",
          "type": "other"
        },
        "xl3": {
          "value": "500ms",
          "type": "other"
        },
        "g": {
          "value": "5000ms",
          "type": "other"
        }
      },
      "transition": {
        "ease": {
          "in": {
            "value": "cubic-bezier(0, 0, 0.40, 1)",
            "type": "other"
          },
          "out": {
            "value": "cubic-bezier(0.50, 0, 1, 1)",
            "type": "other"
          },
          "in-out": {
            "value": "cubic-bezier(0.45, 0, 0.40, 1)",
            "type": "other"
          }
        }
      }
    },
    "borderWidth": {
      "none": {
        "value": "0px",
        "type": "borderWidth"
      },
      "xs": {
        "value": "1px",
        "type": "borderWidth"
      },
      "sm": {
        "value": "2px",
        "type": "borderWidth"
      },
      "md": {
        "value": "4px",
        "type": "borderWidth"
      },
      "lg": {
        "value": "6px",
        "type": "borderWidth"
      },
      "xl": {
        "value": "8px",
        "type": "borderWidth"
      }
    },
    "borderRadius": {
      "0": {
        "value": "{dimension.none}",
        "type": "borderRadius"
      },
      "1": {
        "value": "{dimension.2}",
        "type": "borderRadius"
      },
      "2": {
        "value": "{dimension.3}",
        "type": "borderRadius"
      },
      "3": {
        "value": "{dimension.4}",
        "type": "borderRadius"
      },
      "4": {
        "value": "{dimension.6}",
        "type": "borderRadius"
      },
      "circle": {
        "value": "100%",
        "type": "borderRadius"
      }
    },
    "breakpoint": {
      "xs": {
        "value": "screen and (min-width: 0px) and (max-width:374px)",
        "type": "other"
      },
      "sm": {
        "value": "screen and (min-width: 375px) and (max-width:575px)",
        "type": "other"
      },
      "md": {
        "value": "screen and (min-width: 576px) and (max-width:767px)",
        "type": "other"
      },
      "lg": {
        "value": "screen and (min-width: 768px) and (max-width:991px)",
        "type": "other"
      },
      "xl": {
        "value": "screen and (min-width: 992px) and (max-width:1199px)",
        "type": "other"
      },
      "xxl": {
        "value": "screen and (min-width: 1200px) and (max-width:1400px)",
        "type": "other"
      }
    },
    "fontFamily": {
      "Inter": {
        "value": "Inter",
        "type": "fontFamilies"
      }
    },
    "fontWeight": {
      "100": {
        "value": "100",
        "type": "fontWeights"
      },
      "200": {
        "value": "200",
        "type": "fontWeights"
      },
      "300": {
        "value": "300",
        "type": "fontWeights"
      },
      "400": {
        "value": "400",
        "type": "fontWeights"
      },
      "500": {
        "value": "500",
        "type": "fontWeights"
      },
      "600": {
        "value": "600",
        "type": "fontWeights"
      },
      "700": {
        "value": "700",
        "type": "fontWeights"
      },
      "800": {
        "value": "800",
        "type": "fontWeights"
      },
      "900": {
        "value": "900",
        "type": "fontWeights"
      }
    },
    "lineHeight": {
      "sm": {
        "value": "100%",
        "type": "lineHeights"
      },
      "md": {
        "value": "135%",
        "type": "lineHeights"
      },
      "lg": {
        "value": "150%",
        "type": "lineHeights"
      }
    },
    "letterSpacing": {
      "sm": {
        "value": "-5%",
        "type": "letterSpacing"
      },
      "md": {
        "value": "0%",
        "type": "letterSpacing"
      },
      "lg": {
        "value": "10%",
        "type": "letterSpacing"
      }
    },
    "fontSize": {
      "1": {
        "value": "0.625rem",
        "type": "fontSizes",
        "description": "10px"
      },
      "2": {
        "value": "0.75rem",
        "type": "fontSizes",
        "description": "12px"
      },
      "3": {
        "value": "0.875rem",
        "type": "fontSizes",
        "description": "14px"
      },
      "4": {
        "value": "1rem",
        "type": "fontSizes",
        "description": "16px"
      },
      "5": {
        "value": "1.125rem",
        "type": "fontSizes",
        "description": "18px"
      },
      "6": {
        "value": "1.25rem",
        "type": "fontSizes",
        "description": "20px"
      },
      "7": {
        "value": "1.5rem",
        "type": "fontSizes",
        "description": "24px"
      },
      "8": {
        "value": "1.75rem",
        "type": "fontSizes",
        "description": "28px"
      },
      "9": {
        "value": "2.25rem",
        "type": "fontSizes",
        "description": "36px"
      },
      "10": {
        "value": "2.5rem",
        "type": "fontSizes",
        "description": "40px"
      },
      "11": {
        "value": "2.75rem",
        "type": "fontSizes",
        "description": "44px"
      },
      "12": {
        "value": "3rem",
        "type": "fontSizes",
        "description": "48px"
      },
      "13": {
        "value": "3.375rem",
        "type": "fontSizes",
        "description": "54px"
      },
      "14": {
        "value": "3.875rem",
        "type": "fontSizes",
        "description": "62px"
      },
      "15": {
        "value": "4.375rem",
        "type": "fontSizes",
        "description": "70px"
      },
      "16": {
        "value": "5rem",
        "type": "fontSizes",
        "description": "80px"
      }
    },
    "textTransform": {
      "none": {
        "value": "none",
        "type": "textCase"
      },
      "uppercase": {
        "value": "uppercase",
        "type": "textCase"
      },
      " lowercase": {
        "value": "lowercase",
        "type": "textCase"
      },
      " capitalize": {
        "value": "capitalize",
        "type": "textCase"
      }
    },
    "layer": {
      "1": {
        "value": "-1",
        "type": "other",
        "description": "Usado para a propriedade z-index"
      },
      "2": {
        "value": "0",
        "type": "other",
        "description": "Usado para a propriedade z-index"
      },
      "3": {
        "value": "1",
        "type": "other",
        "description": "Usado para a propriedade z-index"
      },
      "4": {
        "value": "10",
        "type": "other",
        "description": "Usado para a propriedade z-index"
      },
      "5": {
        "value": "50",
        "type": "other",
        "description": "Usado para a propriedade z-index"
      }
    },
    "dimension": {
      "1": {
        "value": "0.25*{scale.base}",
        "type": "dimension"
      },
      "2": {
        "value": "0.5*{scale.base}",
        "type": "dimension"
      },
      "3": {
        "value": "1*{scale.base}",
        "type": "dimension"
      },
      "4": {
        "value": "1.5*{scale.base}",
        "type": "dimension"
      },
      "5": {
        "value": "2*{scale.base}",
        "type": "dimension"
      },
      "6": {
        "value": "3*{scale.base}",
        "type": "dimension"
      },
      "7": {
        "value": "4*{scale.base}",
        "type": "dimension"
      },
      "8": {
        "value": "5*{scale.base}",
        "type": "dimension"
      },
      "9": {
        "value": "6*{scale.base}",
        "type": "dimension"
      },
      "10": {
        "value": "7*{scale.base}",
        "type": "dimension"
      },
      "11": {
        "value": "8*{scale.base}",
        "type": "dimension"
      },
      "12": {
        "value": "9*{scale.base}",
        "type": "dimension"
      },
      "13": {
        "value": "10*{scale.base}",
        "type": "dimension"
      },
      "14": {
        "value": "11*{scale.base}",
        "type": "dimension"
      },
      "15": {
        "value": "12*{scale.base}",
        "type": "dimension"
      },
      "16": {
        "value": "13*{scale.base}",
        "type": "dimension"
      },
      "17": {
        "value": "14*{scale.base}",
        "type": "dimension"
      },
      "18": {
        "value": "15*{scale.base}",
        "type": "dimension"
      },
      "19": {
        "value": "16*{scale.base}",
        "type": "dimension"
      },
      "20": {
        "value": "17*{scale.base}",
        "type": "dimension"
      },
      "21": {
        "value": "18*{scale.base}",
        "type": "dimension"
      },
      "22": {
        "value": "19*{scale.base}",
        "type": "dimension"
      },
      "23": {
        "value": "20*{scale.base}",
        "type": "dimension"
      },
      "24": {
        "value": "21*{scale.base}",
        "type": "dimension"
      },
      "25": {
        "value": "22*{scale.base}",
        "type": "dimension"
      },
      "none": {
        "value": "0px",
        "type": "dimension"
      }
    },
    "scale": {
      "base": {
        "value": "8px",
        "type": "dimension"
      }
    },
    "size": {
      "full": {
        "value": "100%",
        "type": "sizing"
      }
    },
    "spacing": {
      "full": {
        "value": "100%",
        "type": "spacing"
      },
      "gap": {
        "1": {
          "value": "{dimension.1}",
          "type": "spacing"
        },
        "2": {
          "value": "{dimension.2}",
          "type": "spacing"
        },
        "3": {
          "value": "{dimension.3}",
          "type": "spacing"
        },
        "4": {
          "value": "{dimension.4}",
          "type": "spacing"
        },
        "5": {
          "value": "{dimension.5}",
          "type": "spacing"
        },
        "6": {
          "value": "{dimension.6}",
          "type": "spacing"
        },
        "7": {
          "value": "{dimension.7}",
          "type": "spacing"
        },
        "8": {
          "value": "{dimension.8}",
          "type": "spacing"
        },
        "none": {
          "value": "0",
          "type": "spacing"
        }
      },
      "margin": {
        "1": {
          "value": "{dimension.1}",
          "type": "spacing"
        },
        "2": {
          "value": "{dimension.2}",
          "type": "spacing"
        },
        "3": {
          "value": "{dimension.3}",
          "type": "spacing"
        },
        "4": {
          "value": "{dimension.4}",
          "type": "spacing"
        },
        "5": {
          "value": "{dimension.5}",
          "type": "spacing"
        },
        "6": {
          "value": "{dimension.6}",
          "type": "spacing"
        },
        "7": {
          "value": "{dimension.7}",
          "type": "spacing"
        },
        "8": {
          "value": "{dimension.8}",
          "type": "spacing"
        },
        "none": {
          "value": "0",
          "type": "spacing"
        }
      },
      "padding": {
        "1": {
          "value": "{dimension.1}",
          "type": "spacing"
        },
        "2": {
          "value": "{dimension.2}",
          "type": "spacing"
        },
        "3": {
          "value": "{dimension.3}",
          "type": "spacing"
        },
        "4": {
          "value": "{dimension.4}",
          "type": "spacing"
        },
        "5": {
          "value": "{dimension.5}",
          "type": "spacing"
        },
        "6": {
          "value": "{dimension.6}",
          "type": "spacing"
        },
        "7": {
          "value": "{dimension.7}",
          "type": "spacing"
        },
        "8": {
          "value": "{dimension.8}",
          "type": "spacing"
        },
        "none": {
          "value": "0",
          "type": "spacing"
        }
      }
    },
    "color": {
      "base": {
        "white": {
          "value": "hsl(100, 100%, 100%)",
          "type": "color"
        },
        "black": {
          "value": "hsl(0,0%, 0%)",
          "type": "color"
        }
      },
      "charcoal": {
        "50": {
          "value": "hsla(0,0%,90%,1)",
          "type": "color"
        },
        "100": {
          "value": "{color.charcoal.50}",
          "type": "color",
          "$extensions": {
            "studio.tokens": {
              "modify": {
                "type": "darken",
                "value": "{color.amount.1}",
                "space": "hsl"
              }
            }
          }
        },
        "200": {
          "value": "{color.charcoal.50}",
          "type": "color",
          "$extensions": {
            "studio.tokens": {
              "modify": {
                "type": "darken",
                "value": "{color.amount.2}",
                "space": "hsl"
              }
            }
          }
        },
        "300": {
          "value": "{color.charcoal.50}",
          "type": "color",
          "$extensions": {
            "studio.tokens": {
              "modify": {
                "type": "darken",
                "value": "{color.amount.3}",
                "space": "hsl"
              }
            }
          }
        },
        "400": {
          "value": "{color.charcoal.50}",
          "type": "color",
          "$extensions": {
            "studio.tokens": {
              "modify": {
                "type": "darken",
                "value": "{color.amount.4}",
                "space": "hsl"
              }
            }
          }
        },
        "500": {
          "value": "{color.charcoal.50}",
          "type": "color",
          "$extensions": {
            "studio.tokens": {
              "modify": {
                "type": "darken",
                "value": "{color.amount.5}",
                "space": "hsl"
              }
            }
          }
        },
        "600": {
          "value": "{color.charcoal.50}",
          "type": "color",
          "$extensions": {
            "studio.tokens": {
              "modify": {
                "type": "darken",
                "value": "{color.amount.6}",
                "space": "hsl"
              }
            }
          }
        },
        "700": {
          "value": "{color.charcoal.50}",
          "type": "color",
          "$extensions": {
            "studio.tokens": {
              "modify": {
                "type": "darken",
                "value": "{color.amount.7}",
                "space": "hsl"
              }
            }
          }
        },
        "800": {
          "value": "{color.charcoal.50}",
          "type": "color",
          "$extensions": {
            "studio.tokens": {
              "modify": {
                "type": "darken",
                "value": "{color.amount.8}",
                "space": "hsl"
              }
            }
          }
        },
        "900": {
          "value": "{color.charcoal.50}",
          "type": "color",
          "$extensions": {
            "studio.tokens": {
              "modify": {
                "type": "darken",
                "value": "{color.amount.9}",
                "space": "lch"
              }
            }
          }
        }
      },
      "amount": {
        "1": {
          "value": "0.1",
          "type": "other"
        },
        "2": {
          "value": "0.2",
          "type": "other"
        },
        "3": {
          "value": "0.3",
          "type": "other"
        },
        "4": {
          "value": "0.4",
          "type": "other"
        },
        "5": {
          "value": "0.5",
          "type": "other"
        },
        "6": {
          "value": "0.6",
          "type": "other"
        },
        "7": {
          "value": "0.7",
          "type": "other"
        },
        "8": {
          "value": "0.82",
          "type": "other"
        },
        "9": {
          "value": "0.85",
          "type": "other"
        }
      },
      "carbon": {
        "50": {
          "value": "hsla(216,18%,90%,1)",
          "type": "color"
        },
        "100": {
          "value": "{color.carbon.50}",
          "type": "color",
          "$extensions": {
            "studio.tokens": {
              "modify": {
                "type": "darken",
                "value": "{color.amount.1}",
                "space": "hsl"
              }
            }
          }
        },
        "200": {
          "value": "{color.carbon.50}",
          "type": "color",
          "$extensions": {
            "studio.tokens": {
              "modify": {
                "type": "darken",
                "value": "{color.amount.2}",
                "space": "hsl"
              }
            }
          }
        },
        "300": {
          "value": "{color.carbon.50}",
          "type": "color",
          "$extensions": {
            "studio.tokens": {
              "modify": {
                "type": "darken",
                "value": "{color.amount.3}",
                "space": "hsl"
              }
            }
          }
        },
        "400": {
          "value": "{color.carbon.50}",
          "type": "color",
          "$extensions": {
            "studio.tokens": {
              "modify": {
                "type": "darken",
                "value": "{color.amount.4}",
                "space": "hsl"
              }
            }
          }
        },
        "500": {
          "value": "{color.carbon.50}",
          "type": "color",
          "$extensions": {
            "studio.tokens": {
              "modify": {
                "type": "darken",
                "value": "{color.amount.5}",
                "space": "hsl"
              }
            }
          }
        },
        "600": {
          "value": "{color.carbon.50}",
          "type": "color",
          "$extensions": {
            "studio.tokens": {
              "modify": {
                "type": "darken",
                "value": "{color.amount.6}",
                "space": "hsl"
              }
            }
          }
        },
        "700": {
          "value": "{color.carbon.50}",
          "type": "color",
          "$extensions": {
            "studio.tokens": {
              "modify": {
                "type": "darken",
                "value": "{color.amount.7}",
                "space": "hsl"
              }
            }
          }
        },
        "800": {
          "value": "{color.carbon.50}",
          "type": "color",
          "$extensions": {
            "studio.tokens": {
              "modify": {
                "type": "darken",
                "value": "{color.amount.8}",
                "space": "hsl"
              }
            }
          }
        },
        "900": {
          "value": "{color.carbon.50}",
          "type": "color",
          "$extensions": {
            "studio.tokens": {
              "modify": {
                "type": "darken",
                "value": "{color.amount.9}",
                "space": "hsl"
              }
            }
          }
        }
      },
      "blue": {
        "50": {
          "value": "hsla(213,100%,90%,1)",
          "type": "color"
        },
        "100": {
          "value": "{color.blue.50}",
          "type": "color",
          "$extensions": {
            "studio.tokens": {
              "modify": {
                "type": "darken",
                "value": "{color.amount.1}",
                "space": "hsl"
              }
            }
          }
        },
        "200": {
          "value": "{color.blue.50}",
          "type": "color",
          "$extensions": {
            "studio.tokens": {
              "modify": {
                "type": "darken",
                "value": "{color.amount.2}",
                "space": "hsl"
              }
            }
          }
        },
        "300": {
          "value": "{color.blue.50}",
          "type": "color",
          "$extensions": {
            "studio.tokens": {
              "modify": {
                "type": "darken",
                "value": "{color.amount.3}",
                "space": "hsl"
              }
            }
          }
        },
        "400": {
          "value": "{color.blue.50}",
          "type": "color",
          "$extensions": {
            "studio.tokens": {
              "modify": {
                "type": "darken",
                "value": "{color.amount.4}",
                "space": "hsl"
              }
            }
          }
        },
        "500": {
          "value": "{color.blue.50}",
          "type": "color",
          "$extensions": {
            "studio.tokens": {
              "modify": {
                "type": "darken",
                "value": "{color.amount.5}",
                "space": "hsl"
              }
            }
          }
        },
        "600": {
          "value": "{color.blue.50}",
          "type": "color",
          "$extensions": {
            "studio.tokens": {
              "modify": {
                "type": "darken",
                "value": "{color.amount.6}",
                "space": "hsl"
              }
            }
          }
        },
        "700": {
          "value": "{color.blue.50}",
          "type": "color",
          "$extensions": {
            "studio.tokens": {
              "modify": {
                "type": "darken",
                "value": "{color.amount.7}",
                "space": "hsl"
              }
            }
          }
        },
        "800": {
          "value": "{color.blue.50}",
          "type": "color",
          "$extensions": {
            "studio.tokens": {
              "modify": {
                "type": "darken",
                "value": "{color.amount.8}",
                "space": "hsl"
              }
            }
          }
        },
        "900": {
          "value": "{color.blue.50}",
          "type": "color",
          "$extensions": {
            "studio.tokens": {
              "modify": {
                "type": "darken",
                "value": "{color.amount.9}",
                "space": "hsl"
              }
            }
          }
        }
      },
      "cyan": {
        "50": {
          "value": "hsla(193,100%,90%,1)",
          "type": "color"
        },
        "100": {
          "value": "{color.cyan.50}",
          "type": "color",
          "$extensions": {
            "studio.tokens": {
              "modify": {
                "type": "darken",
                "value": "{color.amount.1}",
                "space": "hsl"
              }
            }
          }
        },
        "200": {
          "value": "{color.cyan.50}",
          "type": "color",
          "$extensions": {
            "studio.tokens": {
              "modify": {
                "type": "darken",
                "value": "{color.amount.2}",
                "space": "hsl"
              }
            }
          }
        },
        "300": {
          "value": "{color.cyan.50}",
          "type": "color",
          "$extensions": {
            "studio.tokens": {
              "modify": {
                "type": "darken",
                "value": "{color.amount.3}",
                "space": "hsl"
              }
            }
          }
        },
        "400": {
          "value": "{color.cyan.50}",
          "type": "color",
          "$extensions": {
            "studio.tokens": {
              "modify": {
                "type": "darken",
                "value": "{color.amount.4}",
                "space": "hsl"
              }
            }
          }
        },
        "500": {
          "value": "{color.cyan.50}",
          "type": "color",
          "$extensions": {
            "studio.tokens": {
              "modify": {
                "type": "darken",
                "value": "{color.amount.5}",
                "space": "hsl"
              }
            }
          }
        },
        "600": {
          "value": "{color.cyan.50}",
          "type": "color",
          "$extensions": {
            "studio.tokens": {
              "modify": {
                "type": "darken",
                "value": "{color.amount.6}",
                "space": "hsl"
              }
            }
          }
        },
        "700": {
          "value": "{color.cyan.50}",
          "type": "color",
          "$extensions": {
            "studio.tokens": {
              "modify": {
                "type": "darken",
                "value": "{color.amount.7}",
                "space": "hsl"
              }
            }
          }
        },
        "800": {
          "value": "{color.cyan.50}",
          "type": "color",
          "$extensions": {
            "studio.tokens": {
              "modify": {
                "type": "darken",
                "value": "{color.amount.8}",
                "space": "hsl"
              }
            }
          }
        },
        "900": {
          "value": "{color.cyan.50}",
          "type": "color",
          "$extensions": {
            "studio.tokens": {
              "modify": {
                "type": "darken",
                "value": "{color.amount.9}",
                "space": "hsl"
              }
            }
          }
        }
      },
      "teal": {
        "50": {
          "value": "hsla(166,50%,90%,1)",
          "type": "color"
        },
        "100": {
          "value": "{color.teal.50}",
          "type": "color",
          "$extensions": {
            "studio.tokens": {
              "modify": {
                "type": "darken",
                "value": "{color.amount.1}",
                "space": "hsl"
              }
            }
          }
        },
        "200": {
          "value": "{color.teal.50}",
          "type": "color",
          "$extensions": {
            "studio.tokens": {
              "modify": {
                "type": "darken",
                "value": "{color.amount.2}",
                "space": "hsl"
              }
            }
          }
        },
        "300": {
          "value": "{color.teal.50}",
          "type": "color",
          "$extensions": {
            "studio.tokens": {
              "modify": {
                "type": "darken",
                "value": "{color.amount.3}",
                "space": "hsl"
              }
            }
          }
        },
        "400": {
          "value": "{color.teal.50}",
          "type": "color",
          "$extensions": {
            "studio.tokens": {
              "modify": {
                "type": "darken",
                "value": "{color.amount.4}",
                "space": "hsl"
              }
            }
          }
        },
        "500": {
          "value": "{color.teal.50}",
          "type": "color",
          "$extensions": {
            "studio.tokens": {
              "modify": {
                "type": "darken",
                "value": "{color.amount.5}",
                "space": "hsl"
              }
            }
          }
        },
        "600": {
          "value": "{color.teal.50}",
          "type": "color",
          "$extensions": {
            "studio.tokens": {
              "modify": {
                "type": "darken",
                "value": "{color.amount.6}",
                "space": "hsl"
              }
            }
          }
        },
        "700": {
          "value": "{color.teal.50}",
          "type": "color",
          "$extensions": {
            "studio.tokens": {
              "modify": {
                "type": "darken",
                "value": "{color.amount.7}",
                "space": "hsl"
              }
            }
          }
        },
        "800": {
          "value": "{color.teal.50}",
          "type": "color",
          "$extensions": {
            "studio.tokens": {
              "modify": {
                "type": "darken",
                "value": "{color.amount.8}",
                "space": "hsl"
              }
            }
          }
        },
        "900": {
          "value": "{color.teal.50}",
          "type": "color",
          "$extensions": {
            "studio.tokens": {
              "modify": {
                "type": "darken",
                "value": "{color.amount.9}",
                "space": "hsl"
              }
            }
          }
        }
      },
      "green": {
        "50": {
          "value": "hsla(94,63%,90%,1)",
          "type": "color"
        },
        "100": {
          "value": "{color.green.50}",
          "type": "color",
          "$extensions": {
            "studio.tokens": {
              "modify": {
                "type": "darken",
                "value": "{color.amount.1}",
                "space": "hsl"
              }
            }
          }
        },
        "200": {
          "value": "{color.green.50}",
          "type": "color",
          "$extensions": {
            "studio.tokens": {
              "modify": {
                "type": "darken",
                "value": "{color.amount.2}",
                "space": "hsl"
              }
            }
          }
        },
        "300": {
          "value": "{color.green.50}",
          "type": "color",
          "$extensions": {
            "studio.tokens": {
              "modify": {
                "type": "darken",
                "value": "{color.amount.3}",
                "space": "hsl"
              }
            }
          }
        },
        "400": {
          "value": "{color.green.50}",
          "type": "color",
          "$extensions": {
            "studio.tokens": {
              "modify": {
                "type": "darken",
                "value": "{color.amount.4}",
                "space": "hsl"
              }
            }
          }
        },
        "500": {
          "value": "{color.green.50}",
          "type": "color",
          "$extensions": {
            "studio.tokens": {
              "modify": {
                "type": "darken",
                "value": "{color.amount.5}",
                "space": "hsl"
              }
            }
          }
        },
        "600": {
          "value": "{color.green.50}",
          "type": "color",
          "$extensions": {
            "studio.tokens": {
              "modify": {
                "type": "darken",
                "value": "{color.amount.6}",
                "space": "hsl"
              }
            }
          }
        },
        "700": {
          "value": "{color.green.50}",
          "type": "color",
          "$extensions": {
            "studio.tokens": {
              "modify": {
                "type": "darken",
                "value": "{color.amount.7}",
                "space": "hsl"
              }
            }
          }
        },
        "800": {
          "value": "{color.green.50}",
          "type": "color",
          "$extensions": {
            "studio.tokens": {
              "modify": {
                "type": "darken",
                "value": "{color.amount.8}",
                "space": "hsl"
              }
            }
          }
        },
        "900": {
          "value": "{color.green.50}",
          "type": "color",
          "$extensions": {
            "studio.tokens": {
              "modify": {
                "type": "darken",
                "value": "{color.amount.9}",
                "space": "hsl"
              }
            }
          }
        }
      },
      "yellow": {
        "50": {
          "value": "hsla(60, 100%, 90%,1)",
          "type": "color"
        },
        "100": {
          "value": "{color.yellow.50}",
          "type": "color",
          "$extensions": {
            "studio.tokens": {
              "modify": {
                "type": "darken",
                "value": "{color.amount.1}",
                "space": "hsl"
              }
            }
          }
        },
        "200": {
          "value": "{color.yellow.50}",
          "type": "color",
          "$extensions": {
            "studio.tokens": {
              "modify": {
                "type": "darken",
                "value": "{color.amount.2}",
                "space": "hsl"
              }
            }
          }
        },
        "300": {
          "value": "{color.yellow.50}",
          "type": "color",
          "$extensions": {
            "studio.tokens": {
              "modify": {
                "type": "darken",
                "value": "{color.amount.3}",
                "space": "hsl"
              }
            }
          }
        },
        "400": {
          "value": "{color.yellow.50}",
          "type": "color",
          "$extensions": {
            "studio.tokens": {
              "modify": {
                "type": "darken",
                "value": "{color.amount.4}",
                "space": "hsl"
              }
            }
          }
        },
        "500": {
          "value": "{color.yellow.50}",
          "type": "color",
          "$extensions": {
            "studio.tokens": {
              "modify": {
                "type": "darken",
                "value": "{color.amount.5}",
                "space": "hsl"
              }
            }
          }
        },
        "600": {
          "value": "{color.yellow.50}",
          "type": "color",
          "$extensions": {
            "studio.tokens": {
              "modify": {
                "type": "darken",
                "value": "{color.amount.6}",
                "space": "hsl"
              }
            }
          }
        },
        "700": {
          "value": "{color.yellow.50}",
          "type": "color",
          "$extensions": {
            "studio.tokens": {
              "modify": {
                "type": "darken",
                "value": "{color.amount.7}",
                "space": "hsl"
              }
            }
          }
        },
        "800": {
          "value": "{color.yellow.50}",
          "type": "color",
          "$extensions": {
            "studio.tokens": {
              "modify": {
                "type": "darken",
                "value": "{color.amount.8}",
                "space": "hsl"
              }
            }
          }
        },
        "900": {
          "value": "{color.yellow.50}",
          "type": "color",
          "$extensions": {
            "studio.tokens": {
              "modify": {
                "type": "darken",
                "value": "{color.amount.9}",
                "space": "hsl"
              }
            }
          }
        }
      },
      "orange": {
        "50": {
          "value": "hsla(26,84%,90%,1)",
          "type": "color"
        },
        "100": {
          "value": "{color.orange.50}",
          "type": "color",
          "$extensions": {
            "studio.tokens": {
              "modify": {
                "type": "darken",
                "value": "{color.amount.1}",
                "space": "hsl"
              }
            }
          }
        },
        "200": {
          "value": "{color.orange.50}",
          "type": "color",
          "$extensions": {
            "studio.tokens": {
              "modify": {
                "type": "darken",
                "value": "{color.amount.2}",
                "space": "hsl"
              }
            }
          }
        },
        "300": {
          "value": "{color.orange.50}",
          "type": "color",
          "$extensions": {
            "studio.tokens": {
              "modify": {
                "type": "darken",
                "value": "{color.amount.3}",
                "space": "hsl"
              }
            }
          }
        },
        "400": {
          "value": "{color.orange.50}",
          "type": "color",
          "$extensions": {
            "studio.tokens": {
              "modify": {
                "type": "darken",
                "value": "{color.amount.4}",
                "space": "hsl"
              }
            }
          }
        },
        "500": {
          "value": "{color.orange.50}",
          "type": "color",
          "$extensions": {
            "studio.tokens": {
              "modify": {
                "type": "darken",
                "value": "{color.amount.5}",
                "space": "hsl"
              }
            }
          }
        },
        "600": {
          "value": "{color.orange.50}",
          "type": "color",
          "$extensions": {
            "studio.tokens": {
              "modify": {
                "type": "darken",
                "value": "{color.amount.6}",
                "space": "hsl"
              }
            }
          }
        },
        "700": {
          "value": "{color.orange.50}",
          "type": "color",
          "$extensions": {
            "studio.tokens": {
              "modify": {
                "type": "darken",
                "value": "{color.amount.7}",
                "space": "hsl"
              }
            }
          }
        },
        "800": {
          "value": "{color.orange.50}",
          "type": "color",
          "$extensions": {
            "studio.tokens": {
              "modify": {
                "type": "darken",
                "value": "{color.amount.8}",
                "space": "hsl"
              }
            }
          }
        },
        "900": {
          "value": "{color.orange.50}",
          "type": "color",
          "$extensions": {
            "studio.tokens": {
              "modify": {
                "type": "darken",
                "value": "{color.amount.9}",
                "space": "hsl"
              }
            }
          }
        }
      },
      "red": {
        "50": {
          "value": "hsla(0,70%,90%,1)",
          "type": "color"
        },
        "100": {
          "value": "{color.red.50}",
          "type": "color",
          "$extensions": {
            "studio.tokens": {
              "modify": {
                "type": "darken",
                "value": "{color.amount.1}",
                "space": "hsl"
              }
            }
          }
        },
        "200": {
          "value": "{color.red.50}",
          "type": "color",
          "$extensions": {
            "studio.tokens": {
              "modify": {
                "type": "darken",
                "value": "{color.amount.2}",
                "space": "hsl"
              }
            }
          }
        },
        "300": {
          "value": "{color.red.50}",
          "type": "color",
          "$extensions": {
            "studio.tokens": {
              "modify": {
                "type": "darken",
                "value": "{color.amount.3}",
                "space": "hsl"
              }
            }
          }
        },
        "400": {
          "value": "{color.red.50}",
          "type": "color",
          "$extensions": {
            "studio.tokens": {
              "modify": {
                "type": "darken",
                "value": "{color.amount.4}",
                "space": "hsl"
              }
            }
          }
        },
        "500": {
          "value": "{color.red.50}",
          "type": "color",
          "$extensions": {
            "studio.tokens": {
              "modify": {
                "type": "darken",
                "value": "{color.amount.5}",
                "space": "hsl"
              }
            }
          }
        },
        "600": {
          "value": "{color.red.50}",
          "type": "color",
          "$extensions": {
            "studio.tokens": {
              "modify": {
                "type": "darken",
                "value": "{color.amount.6}",
                "space": "hsl"
              }
            }
          }
        },
        "700": {
          "value": "{color.red.50}",
          "type": "color",
          "$extensions": {
            "studio.tokens": {
              "modify": {
                "type": "darken",
                "value": "{color.amount.7}",
                "space": "hsl"
              }
            }
          }
        },
        "800": {
          "value": "{color.red.50}",
          "type": "color",
          "$extensions": {
            "studio.tokens": {
              "modify": {
                "type": "darken",
                "value": "{color.amount.8}",
                "space": "hsl"
              }
            }
          }
        },
        "900": {
          "value": "{color.red.50}",
          "type": "color",
          "$extensions": {
            "studio.tokens": {
              "modify": {
                "type": "darken",
                "value": "{color.amount.9}",
                "space": "hsl"
              }
            }
          }
        }
      },
      "pink": {
        "50": {
          "value": "hsla(325,63%,90%,1)",
          "type": "color"
        },
        "100": {
          "value": "{color.pink.50}",
          "type": "color",
          "$extensions": {
            "studio.tokens": {
              "modify": {
                "type": "darken",
                "value": "{color.amount.1}",
                "space": "hsl"
              }
            }
          }
        },
        "200": {
          "value": "{color.pink.50}",
          "type": "color",
          "$extensions": {
            "studio.tokens": {
              "modify": {
                "type": "darken",
                "value": "{color.amount.2}",
                "space": "hsl"
              }
            }
          }
        },
        "300": {
          "value": "{color.pink.50}",
          "type": "color",
          "$extensions": {
            "studio.tokens": {
              "modify": {
                "type": "darken",
                "value": "{color.amount.3}",
                "space": "hsl"
              }
            }
          }
        },
        "400": {
          "value": "{color.pink.50}",
          "type": "color",
          "$extensions": {
            "studio.tokens": {
              "modify": {
                "type": "darken",
                "value": "{color.amount.4}",
                "space": "hsl"
              }
            }
          }
        },
        "500": {
          "value": "{color.pink.50}",
          "type": "color",
          "$extensions": {
            "studio.tokens": {
              "modify": {
                "type": "darken",
                "value": "{color.amount.5}",
                "space": "hsl"
              }
            }
          }
        },
        "600": {
          "value": "{color.pink.50}",
          "type": "color",
          "$extensions": {
            "studio.tokens": {
              "modify": {
                "type": "darken",
                "value": "{color.amount.6}",
                "space": "hsl"
              }
            }
          }
        },
        "700": {
          "value": "{color.pink.50}",
          "type": "color",
          "$extensions": {
            "studio.tokens": {
              "modify": {
                "type": "darken",
                "value": "{color.amount.7}",
                "space": "hsl"
              }
            }
          }
        },
        "800": {
          "value": "{color.pink.50}",
          "type": "color",
          "$extensions": {
            "studio.tokens": {
              "modify": {
                "type": "darken",
                "value": "{color.amount.8}",
                "space": "hsl"
              }
            }
          }
        },
        "900": {
          "value": "{color.pink.50}",
          "type": "color",
          "$extensions": {
            "studio.tokens": {
              "modify": {
                "type": "darken",
                "value": "{color.amount.9}",
                "space": "hsl"
              }
            }
          }
        }
      },
      "purple": {
        "50": {
          "value": "hsla(259,63%,90%,1)",
          "type": "color"
        },
        "100": {
          "value": "{color.purple.50}",
          "type": "color",
          "$extensions": {
            "studio.tokens": {
              "modify": {
                "type": "darken",
                "value": "{color.amount.1}",
                "space": "hsl"
              }
            }
          }
        },
        "200": {
          "value": "{color.purple.50}",
          "type": "color",
          "$extensions": {
            "studio.tokens": {
              "modify": {
                "type": "darken",
                "value": "{color.amount.2}",
                "space": "hsl"
              }
            }
          }
        },
        "300": {
          "value": "{color.purple.50}",
          "type": "color",
          "$extensions": {
            "studio.tokens": {
              "modify": {
                "type": "darken",
                "value": "{color.amount.3}",
                "space": "hsl"
              }
            }
          }
        },
        "400": {
          "value": "{color.purple.50}",
          "type": "color",
          "$extensions": {
            "studio.tokens": {
              "modify": {
                "type": "darken",
                "value": "{color.amount.4}",
                "space": "hsl"
              }
            }
          }
        },
        "500": {
          "value": "{color.purple.50}",
          "type": "color",
          "$extensions": {
            "studio.tokens": {
              "modify": {
                "type": "darken",
                "value": "{color.amount.5}",
                "space": "hsl"
              }
            }
          }
        },
        "600": {
          "value": "{color.purple.50}",
          "type": "color",
          "$extensions": {
            "studio.tokens": {
              "modify": {
                "type": "darken",
                "value": "{color.amount.6}",
                "space": "hsl"
              }
            }
          }
        },
        "700": {
          "value": "{color.purple.50}",
          "type": "color",
          "$extensions": {
            "studio.tokens": {
              "modify": {
                "type": "darken",
                "value": "{color.amount.7}",
                "space": "hsl"
              }
            }
          }
        },
        "800": {
          "value": "{color.purple.50}",
          "type": "color",
          "$extensions": {
            "studio.tokens": {
              "modify": {
                "type": "darken",
                "value": "{color.amount.8}",
                "space": "hsl"
              }
            }
          }
        },
        "900": {
          "value": "{color.purple.50}",
          "type": "color",
          "$extensions": {
            "studio.tokens": {
              "modify": {
                "type": "darken",
                "value": "{color.amount.9}",
                "space": "hsl"
              }
            }
          }
        }
      }
    },
    "opacity": {
      "overlay": {
        "value": "0.8",
        "type": "opacity"
      },
      "transparent": {
        "value": "0",
        "type": "opacity"
      }
    },
    "shadow": {
      "none": {
        "value": {
          "x": "0",
          "y": "0",
          "blur": "0",
          "spread": "0",
          "color": "{color.base.black}",
          "type": "dropShadow"
        },
        "type": "boxShadow"
      }
    },
    "paragraphSpacing": {
      "1": {
        "value": "{fontSize.1}",
        "type": "paragraphSpacing"
      },
      "2": {
        "value": "{fontSize.2}",
        "type": "paragraphSpacing"
      },
      "3": {
        "value": "{fontSize.3}",
        "type": "paragraphSpacing"
      },
      "4": {
        "value": "{fontSize.4}",
        "type": "paragraphSpacing"
      },
      "5": {
        "value": "{fontSize.5}",
        "type": "paragraphSpacing"
      },
      "6": {
        "value": "{fontSize.6}",
        "type": "paragraphSpacing"
      },
      "7": {
        "value": "{fontSize.7}",
        "type": "paragraphSpacing"
      },
      "8": {
        "value": "{fontSize.8}",
        "type": "paragraphSpacing"
      },
      "9": {
        "value": "{fontSize.9}",
        "type": "paragraphSpacing"
      },
      "10": {
        "value": "{fontSize.10}",
        "type": "paragraphSpacing"
      },
      "11": {
        "value": "{fontSize.11}",
        "type": "paragraphSpacing"
      },
      "12": {
        "value": "{fontSize.12}",
        "type": "paragraphSpacing"
      },
      "13": {
        "value": "{fontSize.13}",
        "type": "paragraphSpacing"
      },
      "14": {
        "value": "{fontSize.14}",
        "type": "paragraphSpacing"
      },
      "15": {
        "value": "{fontSize.15}",
        "type": "paragraphSpacing"
      },
      "16": {
        "value": "{fontSize.16}",
        "type": "paragraphSpacing"
      }
    },
    "typographhy": {
      "footnote": {
        "extraLight": {
          "value": {
            "fontFamily": "{fontFamily.Inter}",
            "lineHeight": "{lineHeight.md}",
            "fontSize": "{fontSize.2}",
            "letterSpacing": "{letterSpacing.md}",
            "paragraphSpacing": "{paragraphSpacing.2}",
            "fontWeight": "{fontWeight.200}"
          },
          "type": "typography"
        },
        "regular": {
          "value": {
            "fontFamily": "{fontFamily.Inter}",
            "lineHeight": "{lineHeight.md}",
            "fontSize": "{fontSize.2}",
            "letterSpacing": "{letterSpacing.md}",
            "paragraphSpacing": "{paragraphSpacing.2}",
            "fontWeight": "{fontWeight.400}"
          },
          "type": "typography"
        },
        "semiBold": {
          "value": {
            "fontFamily": "{fontFamily.Inter}",
            "lineHeight": "{lineHeight.md}",
            "fontSize": "{fontSize.2}",
            "letterSpacing": "{letterSpacing.md}",
            "paragraphSpacing": "{paragraphSpacing.2}",
            "fontWeight": "{fontWeight.600}"
          },
          "type": "typography"
        },
        "extraBold": {
          "value": {
            "fontFamily": "{fontFamily.Inter}",
            "lineHeight": "{lineHeight.md}",
            "fontSize": "{fontSize.2}",
            "letterSpacing": "{letterSpacing.md}",
            "paragraphSpacing": "{paragraphSpacing.2}",
            "fontWeight": "{fontWeight.800}"
          },
          "type": "typography"
        }
      },
      "body": {
        "extraLight": {
          "value": {
            "fontFamily": "{fontFamily.Inter}",
            "lineHeight": "{lineHeight.md}",
            "fontSize": "{fontSize.3}",
            "letterSpacing": "{letterSpacing.md}",
            "paragraphSpacing": "{paragraphSpacing.3}",
            "fontWeight": "{fontWeight.200}"
          },
          "type": "typography"
        },
        "regular": {
          "value": {
            "fontFamily": "{fontFamily.Inter}",
            "lineHeight": "{lineHeight.md}",
            "fontSize": "{fontSize.3}",
            "letterSpacing": "{letterSpacing.md}",
            "paragraphSpacing": "{paragraphSpacing.3}",
            "fontWeight": "{fontWeight.400}"
          },
          "type": "typography"
        },
        "semiBold": {
          "value": {
            "fontFamily": "{fontFamily.Inter}",
            "lineHeight": "{lineHeight.md}",
            "fontSize": "{fontSize.3}",
            "letterSpacing": "{letterSpacing.md}",
            "paragraphSpacing": "{paragraphSpacing.3}",
            "fontWeight": "{fontWeight.600}"
          },
          "type": "typography"
        },
        "extraBold": {
          "value": {
            "fontFamily": "{fontFamily.Inter}",
            "lineHeight": "{lineHeight.md}",
            "fontSize": "{fontSize.3}",
            "letterSpacing": "{letterSpacing.md}",
            "paragraphSpacing": "{paragraphSpacing.3}",
            "fontWeight": "{fontWeight.800}"
          },
          "type": "typography"
        }
      },
      "bodyMedium": {
        "extraLight": {
          "value": {
            "fontFamily": "{fontFamily.Inter}",
            "lineHeight": "{lineHeight.md}",
            "fontSize": "{fontSize.4}",
            "letterSpacing": "{letterSpacing.md}",
            "paragraphSpacing": "{paragraphSpacing.4}",
            "fontWeight": "{fontWeight.200}"
          },
          "type": "typography"
        },
        "regular": {
          "value": {
            "fontFamily": "{fontFamily.Inter}",
            "lineHeight": "{lineHeight.md}",
            "fontSize": "{fontSize.4}",
            "letterSpacing": "{letterSpacing.md}",
            "paragraphSpacing": "{paragraphSpacing.4}",
            "fontWeight": "{fontWeight.400}"
          },
          "type": "typography"
        },
        "semiBold": {
          "value": {
            "fontFamily": "{fontFamily.Inter}",
            "lineHeight": "{lineHeight.md}",
            "fontSize": "{fontSize.4}",
            "letterSpacing": "{letterSpacing.md}",
            "paragraphSpacing": "{paragraphSpacing.4}",
            "fontWeight": "{fontWeight.600}"
          },
          "type": "typography"
        },
        "extraBold": {
          "value": {
            "fontFamily": "{fontFamily.Inter}",
            "lineHeight": "{lineHeight.md}",
            "fontSize": "{fontSize.4}",
            "letterSpacing": "{letterSpacing.md}",
            "paragraphSpacing": "{paragraphSpacing.4}",
            "fontWeight": "{fontWeight.800}"
          },
          "type": "typography"
        }
      },
      "bodyLarge": {
        "extraLight": {
          "value": {
            "fontFamily": "{fontFamily.Inter}",
            "lineHeight": "{lineHeight.md}",
            "fontSize": "{fontSize.5}",
            "letterSpacing": "{letterSpacing.md}",
            "paragraphSpacing": "{paragraphSpacing.5}",
            "fontWeight": "{fontWeight.200}"
          },
          "type": "typography"
        },
        "regular": {
          "value": {
            "fontFamily": "{fontFamily.Inter}",
            "lineHeight": "{lineHeight.md}",
            "fontSize": "{fontSize.5}",
            "letterSpacing": "{letterSpacing.md}",
            "paragraphSpacing": "{paragraphSpacing.5}",
            "fontWeight": "{fontWeight.400}"
          },
          "type": "typography"
        },
        "semiBold": {
          "value": {
            "fontFamily": "{fontFamily.Inter}",
            "lineHeight": "{lineHeight.md}",
            "fontSize": "{fontSize.5}",
            "letterSpacing": "{letterSpacing.md}",
            "paragraphSpacing": "{paragraphSpacing.5}",
            "fontWeight": "{fontWeight.600}"
          },
          "type": "typography"
        },
        "extraBold": {
          "value": {
            "fontFamily": "{fontFamily.Inter}",
            "lineHeight": "{lineHeight.md}",
            "fontSize": "{fontSize.5}",
            "letterSpacing": "{letterSpacing.md}",
            "paragraphSpacing": "{paragraphSpacing.5}",
            "fontWeight": "{fontWeight.800}"
          },
          "type": "typography"
        }
      },
      "h3": {
        "extraLight": {
          "value": {
            "fontFamily": "{fontFamily.Inter}",
            "lineHeight": "{lineHeight.md}",
            "fontSize": "{fontSize.7}",
            "letterSpacing": "{letterSpacing.md}",
            "paragraphSpacing": "{paragraphSpacing.7}",
            "fontWeight": "{fontWeight.200}"
          },
          "type": "typography"
        },
        "regular": {
          "value": {
            "fontFamily": "{fontFamily.Inter}",
            "lineHeight": "{lineHeight.md}",
            "fontSize": "{fontSize.7}",
            "letterSpacing": "{letterSpacing.md}",
            "paragraphSpacing": "{paragraphSpacing.7}",
            "fontWeight": "{fontWeight.400}"
          },
          "type": "typography"
        },
        "semiBold": {
          "value": {
            "fontFamily": "{fontFamily.Inter}",
            "lineHeight": "{lineHeight.md}",
            "fontSize": "{fontSize.7}",
            "letterSpacing": "{letterSpacing.md}",
            "paragraphSpacing": "{paragraphSpacing.7}",
            "fontWeight": "{fontWeight.600}"
          },
          "type": "typography"
        },
        "extraBold": {
          "value": {
            "fontFamily": "{fontFamily.Inter}",
            "lineHeight": "{lineHeight.md}",
            "fontSize": "{fontSize.7}",
            "letterSpacing": "{letterSpacing.md}",
            "paragraphSpacing": "{paragraphSpacing.7}",
            "fontWeight": "{fontWeight.800}"
          },
          "type": "typography"
        }
      },
      "h2": {
        "extraLight": {
          "value": {
            "fontFamily": "{fontFamily.Inter}",
            "lineHeight": "{lineHeight.md}",
            "fontSize": "{fontSize.8}",
            "letterSpacing": "{letterSpacing.md}",
            "paragraphSpacing": "{paragraphSpacing.8}",
            "fontWeight": "{fontWeight.200}"
          },
          "type": "typography"
        },
        "regular": {
          "value": {
            "fontFamily": "{fontFamily.Inter}",
            "lineHeight": "{lineHeight.md}",
            "fontSize": "{fontSize.8}",
            "letterSpacing": "{letterSpacing.md}",
            "paragraphSpacing": "{paragraphSpacing.8}",
            "fontWeight": "{fontWeight.400}"
          },
          "type": "typography"
        },
        "semiBold": {
          "value": {
            "fontFamily": "{fontFamily.Inter}",
            "lineHeight": "{lineHeight.md}",
            "fontSize": "{fontSize.8}",
            "letterSpacing": "{letterSpacing.md}",
            "paragraphSpacing": "{paragraphSpacing.8}",
            "fontWeight": "{fontWeight.600}"
          },
          "type": "typography"
        },
        "extraBold": {
          "value": {
            "fontFamily": "{fontFamily.Inter}",
            "lineHeight": "{lineHeight.md}",
            "fontSize": "{fontSize.8}",
            "letterSpacing": "{letterSpacing.md}",
            "paragraphSpacing": "{paragraphSpacing.8}",
            "fontWeight": "{fontWeight.800}"
          },
          "type": "typography"
        }
      },
      "h1": {
        "extraLight": {
          "value": {
            "fontFamily": "{fontFamily.Inter}",
            "lineHeight": "{lineHeight.md}",
            "fontSize": "{fontSize.10}",
            "letterSpacing": "{letterSpacing.md}",
            "paragraphSpacing": "{paragraphSpacing.10}",
            "fontWeight": "{fontWeight.200}"
          },
          "type": "typography"
        },
        "regular": {
          "value": {
            "fontFamily": "{fontFamily.Inter}",
            "lineHeight": "{lineHeight.md}",
            "fontSize": "{fontSize.10}",
            "letterSpacing": "{letterSpacing.md}",
            "paragraphSpacing": "{paragraphSpacing.10}",
            "fontWeight": "{fontWeight.400}"
          },
          "type": "typography"
        },
        "semiBold": {
          "value": {
            "fontFamily": "{fontFamily.Inter}",
            "lineHeight": "{lineHeight.md}",
            "fontSize": "{fontSize.10}",
            "letterSpacing": "{letterSpacing.md}",
            "paragraphSpacing": "{paragraphSpacing.10}",
            "fontWeight": "{fontWeight.600}"
          },
          "type": "typography"
        },
        "extraBold": {
          "value": {
            "fontFamily": "{fontFamily.Inter}",
            "lineHeight": "{lineHeight.md}",
            "fontSize": "{fontSize.10}",
            "letterSpacing": "{letterSpacing.md}",
            "paragraphSpacing": "{paragraphSpacing.10}",
            "fontWeight": "{fontWeight.800}"
          },
          "type": "typography"
        }
      }
    }
  },
  "$themes": [],
  "$metadata": {
    "tokenSetOrder": [
      "Core"
    ]
  }
}